{
  "monthLabel": "4월",
  "sourceFileNote": "제이엘정형외과_키워드_배점표_3월.xlsx",
  "hospitalName": "제이엘정형외과",
  "hospitalNames": [
    "제이엘정형외과"
  ],
  "hospitalDomains": [
    "https://jlorthopedics.com/"
  ],
  "hospitalBlogBases": [
    "https://blog.naver.com/muscle118072",
    "https://blog.naver.com/jlorthopedics"
  ],
  "manualRanks": {},
  "manualRanksByTab": {},
  "regionDefault": "",
  "keywords": [
    "마곡정형외과",
    "화곡역정형외과",
    "김포정형외과",
    "마곡역정형외과",
    "발산역정형외과",
    "화곡동정형외과",
    "강서구정형외과",
    "강서정형외과",
    "마곡동정형외과",
    "발산정형외과",
    "김포신경외과",
    "우장산역정형외과",
    "가양동정형외과",
    "신방화역정형외과",
    "강서구신경외과",
    "강서신경외과",
    "송정역정형외과",
    "마곡신경외과",
    "화곡역신경외과",
    "마곡역신경외과",
    "원그로브병원",
    "원그로브정형외과",
    "발산역신경외과",
    "화곡동신경외과",
    "발산역허리디스크",
    "발산신경외과",
    "마곡동신경외과",
    "우장산역신경외과",
    "가양동신경외과",
    "발산역오십견",
    "발산역어깨통증",
    "마곡역퇴행성관절염",
    "마곡역오십견",
    "발산역퇴행성관절염",
    "마곡역무릎병원",
    "발산역디스크치료",
    "발산역족저근막염",
    "발산역족부정형외과",
    "발산역아킬레스건염",
    "발산역석회화건염",
    "발산역발목치료",
    "발산역발목정형외과",
    "발산역발목병원",
    "발산역발목관절염",
    "발산역무지외반증",
    "발산역무릎정형외과",
    "발산역무릎관절염",
    "마곡퇴행성관절염",
    "마곡족저근막염",
    "마곡족부정형외과",
    "마곡오십견",
    "마곡역족저근막염",
    "마곡역족부정형외과",
    "마곡역아킬레스건염",
    "마곡역석회화건염",
    "마곡역발목정형외과",
    "마곡역발목병원",
    "마곡역발목관절염",
    "마곡역무릎정형외과",
    "화곡역무릎관절염",
    "공항시장역테니스엘보",
    "공항시장역정형외과",
    "우장산역어깨충돌증후군",
    "개화역척추관협착증",
    "개화역정형외과",
    "김포경추신경근병증",
    "신월동척추분리증",
    "까치산역테니스엘보",
    "신월손목터널증후군",
    "신월정형외과",
    "강서정형외과골프엘보",
    "우장산역척추분리증",
    "송정역척추골절",
    "마곡연골연화증",
    "가양동무릎병원",
    "가양동무릎",
    "송정역척추",
    "우장산역척추",
    "신월손목",
    "김포경추",
    "화곡역무릎",
    "신월동척추",
    "원그로브병원무릎인대",
    "원그로브병원손목건초염",
    "행신역어깨탈구",
    "신방화역좌골신경통",
    "공항동어깨충돌증후군",
    "신방화좌골신경통",
    "오정구근막통증증후군",
    "송정척추골절",
    "강서신경외과경추신경근병증",
    "행신역회전근개파열",
    "행신회전근개파열",
    "발산어깨통증",
    "까치산역신경외과",
    "행신동연골연화증",
    "까치산신경외과",
    "행신연골연화증",
    "우장산역무지외반증",
    "우장산무지외반증",
    "까치산역발목터널증후군",
    "까치산발목터널증후군",
    "가양동무릎관절염",
    "발산족저근막염",
    "공항동슬개대퇴증후군",
    "공항동슬개",
    "오정구아킬레스건파열",
    "오정구아킬레스건",
    "송정역무릎병원",
    "송정역손목터널증후군",
    "송정역무릎연골손상",
    "공항시장역반월상연골판파열",
    "발산관절탈구",
    "발산역관절탈구",
    "우장산역수근관증후군",
    "우장산수근관증후군",
    "등촌정형외과골프엘보",
    "등촌정형외과",
    "등촌골프엘보",
    "행신역정형외과근막통증증후군",
    "행신정형외과근막통증증후군",
    "행신역근막통증증후군",
    "행신역근막통증",
    "발산역어깨충돌증후군",
    "발산어깨충돌증후군",
    "김포정형외과관절탈구",
    "김포관절탈구",
    "화곡역정형외과무릎관절염",
    "화곡정형외과무릎관절염",
    "화곡무릎관절염",
    "강서정형외과인대손상",
    "마곡허리디스크",
    "마곡역무릎관절염",
    "강서인대손상",
    "족저근막염",
    "무지외반증",
    "목디스크증상",
    "팔꿈치통증",
    "고관절통증",
    "발목접질렀을때",
    "방아쇠수지증후군",
    "목이아파요",
    "테니스엘보",
    "발목통증",
    "지간신경종",
    "발목인대파열",
    "아킬레스건염",
    "발목염좌",
    "골프엘보",
    "손이저린이유",
    "테니스엘보치료",
    "아킬레스건파열",
    "대퇴골두무혈성괴사",
    "PRP주사",
    "팔이저려요",
    "엄지손가락저림",
    "손가락정형외과",
    "고관절염증",
    "손끝이저려요",
    "무지외반증증상",
    "발목관절염",
    "무릎뚝소리",
    "발목이아파요",
    "족저근막염원인",
    "무지외반증치료",
    "발바닥찌릿",
    "발목염좌치료",
    "무릎앞쪽통증",
    "족부정형외과",
    "무릎정형외과",
    "손목터널증후군원인",
    "고관절병원",
    "어깨통증치료병원",
    "고관절치료",
    "무지외반증원인",
    "수부정형외과",
    "발목병원",
    "무릎통증치료",
    "발목정형외과",
    "허리통증치료",
    "척추관협착증치료법",
    "발목염좌증상",
    "발정형외과",
    "손목건초염병원",
    "팔꿈치주사",
    "척추전방전위증치료",
    "고관절정형외과",
    "뒷목이아플때",
    "발목염좌병원",
    "족저근막염치료법",
    "손저림치료",
    "발목관절염증상",
    "퇴행성고관절염",
    "발목이아플때",
    "엄지발가락이아파요",
    "발목관절염치료",
    "어깨치료잘하는병원",
    "발목통증치료",
    "석회화건염치료",
    "발목관절염병원",
    "무릎치료잘하는곳",
    "무릎통증치료법",
    "목이아픈원인",
    "발가락통증치료"
  ],
  "rowsBySheetKey": {
    "regional-pc": [
      {
        "region": "",
        "keyword": "마곡정형외과"
      },
      {
        "region": "",
        "keyword": "화곡역정형외과"
      },
      {
        "region": "",
        "keyword": "김포정형외과"
      },
      {
        "region": "",
        "keyword": "마곡역정형외과"
      },
      {
        "region": "",
        "keyword": "발산역정형외과"
      },
      {
        "region": "",
        "keyword": "화곡동정형외과"
      },
      {
        "region": "",
        "keyword": "강서구정형외과"
      },
      {
        "region": "",
        "keyword": "강서정형외과"
      },
      {
        "region": "",
        "keyword": "마곡동정형외과"
      },
      {
        "region": "",
        "keyword": "발산정형외과"
      },
      {
        "region": "",
        "keyword": "김포신경외과"
      },
      {
        "region": "",
        "keyword": "우장산역정형외과"
      },
      {
        "region": "",
        "keyword": "가양동정형외과"
      },
      {
        "region": "",
        "keyword": "신방화역정형외과"
      },
      {
        "region": "",
        "keyword": "강서구신경외과"
      },
      {
        "region": "",
        "keyword": "강서신경외과"
      },
      {
        "region": "",
        "keyword": "송정역정형외과"
      },
      {
        "region": "",
        "keyword": "마곡신경외과"
      },
      {
        "region": "",
        "keyword": "화곡역신경외과"
      },
      {
        "region": "",
        "keyword": "마곡역신경외과"
      },
      {
        "region": "",
        "keyword": "원그로브병원"
      },
      {
        "region": "",
        "keyword": "원그로브정형외과"
      },
      {
        "region": "",
        "keyword": "발산역신경외과"
      },
      {
        "region": "",
        "keyword": "화곡동신경외과"
      },
      {
        "region": "",
        "keyword": "발산역허리디스크"
      },
      {
        "region": "",
        "keyword": "발산신경외과"
      },
      {
        "region": "",
        "keyword": "마곡동신경외과"
      },
      {
        "region": "",
        "keyword": "우장산역신경외과"
      },
      {
        "region": "",
        "keyword": "가양동신경외과"
      },
      {
        "region": "",
        "keyword": "발산역오십견"
      },
      {
        "region": "",
        "keyword": "발산역어깨통증"
      },
      {
        "region": "",
        "keyword": "마곡역퇴행성관절염"
      },
      {
        "region": "",
        "keyword": "마곡역오십견"
      },
      {
        "region": "",
        "keyword": "발산역퇴행성관절염"
      },
      {
        "region": "",
        "keyword": "마곡역무릎병원"
      },
      {
        "region": "",
        "keyword": "발산역디스크치료"
      },
      {
        "region": "",
        "keyword": "발산역족저근막염"
      },
      {
        "region": "",
        "keyword": "발산역족부정형외과"
      },
      {
        "region": "",
        "keyword": "발산역아킬레스건염"
      },
      {
        "region": "",
        "keyword": "발산역석회화건염"
      },
      {
        "region": "",
        "keyword": "발산역발목치료"
      },
      {
        "region": "",
        "keyword": "발산역발목정형외과"
      },
      {
        "region": "",
        "keyword": "발산역발목병원"
      },
      {
        "region": "",
        "keyword": "발산역발목관절염"
      },
      {
        "region": "",
        "keyword": "발산역무지외반증"
      },
      {
        "region": "",
        "keyword": "발산역무릎정형외과"
      },
      {
        "region": "",
        "keyword": "발산역무릎관절염"
      },
      {
        "region": "",
        "keyword": "마곡퇴행성관절염"
      },
      {
        "region": "",
        "keyword": "마곡족저근막염"
      },
      {
        "region": "",
        "keyword": "마곡족부정형외과"
      },
      {
        "region": "",
        "keyword": "마곡오십견"
      },
      {
        "region": "",
        "keyword": "마곡역족저근막염"
      },
      {
        "region": "",
        "keyword": "마곡역족부정형외과"
      },
      {
        "region": "",
        "keyword": "마곡역아킬레스건염"
      },
      {
        "region": "",
        "keyword": "마곡역석회화건염"
      },
      {
        "region": "",
        "keyword": "마곡역발목정형외과"
      },
      {
        "region": "",
        "keyword": "마곡역발목병원"
      },
      {
        "region": "",
        "keyword": "마곡역발목관절염"
      },
      {
        "region": "",
        "keyword": "마곡역무릎정형외과"
      },
      {
        "region": "",
        "keyword": "화곡역무릎관절염"
      },
      {
        "region": "",
        "keyword": "공항시장역테니스엘보"
      },
      {
        "region": "",
        "keyword": "공항시장역정형외과"
      },
      {
        "region": "",
        "keyword": "우장산역어깨충돌증후군"
      },
      {
        "region": "",
        "keyword": "개화역척추관협착증"
      },
      {
        "region": "",
        "keyword": "개화역정형외과"
      },
      {
        "region": "",
        "keyword": "김포경추신경근병증"
      },
      {
        "region": "",
        "keyword": "신월동척추분리증"
      },
      {
        "region": "",
        "keyword": "까치산역테니스엘보"
      },
      {
        "region": "",
        "keyword": "신월손목터널증후군"
      },
      {
        "region": "",
        "keyword": "신월정형외과"
      },
      {
        "region": "",
        "keyword": "강서정형외과골프엘보"
      },
      {
        "region": "",
        "keyword": "우장산역척추분리증"
      },
      {
        "region": "",
        "keyword": "송정역척추골절"
      },
      {
        "region": "",
        "keyword": "마곡연골연화증"
      },
      {
        "region": "",
        "keyword": "가양동무릎병원"
      },
      {
        "region": "",
        "keyword": "가양동무릎"
      },
      {
        "region": "",
        "keyword": "송정역척추"
      },
      {
        "region": "",
        "keyword": "우장산역척추"
      },
      {
        "region": "",
        "keyword": "신월손목"
      },
      {
        "region": "",
        "keyword": "김포경추"
      },
      {
        "region": "",
        "keyword": "화곡역무릎"
      },
      {
        "region": "",
        "keyword": "신월동척추"
      },
      {
        "region": "",
        "keyword": "원그로브병원무릎인대"
      },
      {
        "region": "",
        "keyword": "원그로브병원손목건초염"
      },
      {
        "region": "",
        "keyword": "행신역어깨탈구"
      },
      {
        "region": "",
        "keyword": "신방화역좌골신경통"
      },
      {
        "region": "",
        "keyword": "공항동어깨충돌증후군"
      },
      {
        "region": "",
        "keyword": "신방화좌골신경통"
      },
      {
        "region": "",
        "keyword": "오정구근막통증증후군"
      },
      {
        "region": "",
        "keyword": "송정척추골절"
      },
      {
        "region": "",
        "keyword": "강서신경외과경추신경근병증"
      },
      {
        "region": "",
        "keyword": "행신역회전근개파열"
      },
      {
        "region": "",
        "keyword": "행신회전근개파열"
      },
      {
        "region": "",
        "keyword": "발산어깨통증"
      },
      {
        "region": "",
        "keyword": "까치산역신경외과"
      },
      {
        "region": "",
        "keyword": "행신동연골연화증"
      },
      {
        "region": "",
        "keyword": "까치산신경외과"
      },
      {
        "region": "",
        "keyword": "행신연골연화증"
      },
      {
        "region": "",
        "keyword": "우장산역무지외반증"
      },
      {
        "region": "",
        "keyword": "우장산무지외반증"
      },
      {
        "region": "",
        "keyword": "까치산역발목터널증후군"
      },
      {
        "region": "",
        "keyword": "까치산발목터널증후군"
      },
      {
        "region": "",
        "keyword": "가양동무릎관절염"
      },
      {
        "region": "",
        "keyword": "발산족저근막염"
      },
      {
        "region": "",
        "keyword": "공항동슬개대퇴증후군"
      },
      {
        "region": "",
        "keyword": "공항동슬개"
      },
      {
        "region": "",
        "keyword": "오정구아킬레스건파열"
      },
      {
        "region": "",
        "keyword": "오정구아킬레스건"
      },
      {
        "region": "",
        "keyword": "송정역무릎병원"
      },
      {
        "region": "",
        "keyword": "송정역손목터널증후군"
      },
      {
        "region": "",
        "keyword": "송정역무릎연골손상"
      },
      {
        "region": "",
        "keyword": "공항시장역반월상연골판파열"
      },
      {
        "region": "",
        "keyword": "발산관절탈구"
      },
      {
        "region": "",
        "keyword": "발산역관절탈구"
      },
      {
        "region": "",
        "keyword": "우장산역수근관증후군"
      },
      {
        "region": "",
        "keyword": "우장산수근관증후군"
      },
      {
        "region": "",
        "keyword": "등촌정형외과골프엘보"
      },
      {
        "region": "",
        "keyword": "등촌정형외과"
      },
      {
        "region": "",
        "keyword": "등촌골프엘보"
      },
      {
        "region": "",
        "keyword": "행신역정형외과근막통증증후군"
      },
      {
        "region": "",
        "keyword": "행신정형외과근막통증증후군"
      },
      {
        "region": "",
        "keyword": "행신역근막통증증후군"
      },
      {
        "region": "",
        "keyword": "행신역근막통증"
      },
      {
        "region": "",
        "keyword": "발산역어깨충돌증후군"
      },
      {
        "region": "",
        "keyword": "발산어깨충돌증후군"
      },
      {
        "region": "",
        "keyword": "김포정형외과관절탈구"
      },
      {
        "region": "",
        "keyword": "김포관절탈구"
      },
      {
        "region": "",
        "keyword": "화곡역정형외과무릎관절염"
      },
      {
        "region": "",
        "keyword": "화곡정형외과무릎관절염"
      },
      {
        "region": "",
        "keyword": "화곡무릎관절염"
      },
      {
        "region": "",
        "keyword": "강서정형외과인대손상"
      },
      {
        "region": "",
        "keyword": "마곡허리디스크"
      },
      {
        "region": "",
        "keyword": "마곡역무릎관절염"
      },
      {
        "region": "",
        "keyword": "강서인대손상"
      }
    ],
    "regional-mob": [
      {
        "region": "",
        "keyword": "마곡정형외과"
      },
      {
        "region": "",
        "keyword": "화곡역정형외과"
      },
      {
        "region": "",
        "keyword": "김포정형외과"
      },
      {
        "region": "",
        "keyword": "마곡역정형외과"
      },
      {
        "region": "",
        "keyword": "발산역정형외과"
      },
      {
        "region": "",
        "keyword": "화곡동정형외과"
      },
      {
        "region": "",
        "keyword": "강서구정형외과"
      },
      {
        "region": "",
        "keyword": "강서정형외과"
      },
      {
        "region": "",
        "keyword": "마곡동정형외과"
      },
      {
        "region": "",
        "keyword": "발산정형외과"
      },
      {
        "region": "",
        "keyword": "김포신경외과"
      },
      {
        "region": "",
        "keyword": "우장산역정형외과"
      },
      {
        "region": "",
        "keyword": "가양동정형외과"
      },
      {
        "region": "",
        "keyword": "신방화역정형외과"
      },
      {
        "region": "",
        "keyword": "강서구신경외과"
      },
      {
        "region": "",
        "keyword": "강서신경외과"
      },
      {
        "region": "",
        "keyword": "송정역정형외과"
      },
      {
        "region": "",
        "keyword": "마곡신경외과"
      },
      {
        "region": "",
        "keyword": "화곡역신경외과"
      },
      {
        "region": "",
        "keyword": "마곡역신경외과"
      },
      {
        "region": "",
        "keyword": "원그로브병원"
      },
      {
        "region": "",
        "keyword": "원그로브정형외과"
      },
      {
        "region": "",
        "keyword": "발산역신경외과"
      },
      {
        "region": "",
        "keyword": "화곡동신경외과"
      },
      {
        "region": "",
        "keyword": "발산역허리디스크"
      },
      {
        "region": "",
        "keyword": "발산신경외과"
      },
      {
        "region": "",
        "keyword": "마곡동신경외과"
      },
      {
        "region": "",
        "keyword": "우장산역신경외과"
      },
      {
        "region": "",
        "keyword": "가양동신경외과"
      },
      {
        "region": "",
        "keyword": "발산역오십견"
      },
      {
        "region": "",
        "keyword": "발산역어깨통증"
      },
      {
        "region": "",
        "keyword": "마곡역퇴행성관절염"
      },
      {
        "region": "",
        "keyword": "마곡역오십견"
      },
      {
        "region": "",
        "keyword": "발산역퇴행성관절염"
      },
      {
        "region": "",
        "keyword": "마곡역무릎병원"
      },
      {
        "region": "",
        "keyword": "발산역디스크치료"
      },
      {
        "region": "",
        "keyword": "발산역족저근막염"
      },
      {
        "region": "",
        "keyword": "발산역족부정형외과"
      },
      {
        "region": "",
        "keyword": "발산역아킬레스건염"
      },
      {
        "region": "",
        "keyword": "발산역석회화건염"
      },
      {
        "region": "",
        "keyword": "발산역발목치료"
      },
      {
        "region": "",
        "keyword": "발산역발목정형외과"
      },
      {
        "region": "",
        "keyword": "발산역발목병원"
      },
      {
        "region": "",
        "keyword": "발산역발목관절염"
      },
      {
        "region": "",
        "keyword": "발산역무지외반증"
      },
      {
        "region": "",
        "keyword": "발산역무릎정형외과"
      },
      {
        "region": "",
        "keyword": "발산역무릎관절염"
      },
      {
        "region": "",
        "keyword": "마곡퇴행성관절염"
      },
      {
        "region": "",
        "keyword": "마곡족저근막염"
      },
      {
        "region": "",
        "keyword": "마곡족부정형외과"
      },
      {
        "region": "",
        "keyword": "마곡오십견"
      },
      {
        "region": "",
        "keyword": "마곡역족저근막염"
      },
      {
        "region": "",
        "keyword": "마곡역족부정형외과"
      },
      {
        "region": "",
        "keyword": "마곡역아킬레스건염"
      },
      {
        "region": "",
        "keyword": "마곡역석회화건염"
      },
      {
        "region": "",
        "keyword": "마곡역발목정형외과"
      },
      {
        "region": "",
        "keyword": "마곡역발목병원"
      },
      {
        "region": "",
        "keyword": "마곡역발목관절염"
      },
      {
        "region": "",
        "keyword": "마곡역무릎정형외과"
      },
      {
        "region": "",
        "keyword": "화곡역무릎관절염"
      },
      {
        "region": "",
        "keyword": "공항시장역테니스엘보"
      },
      {
        "region": "",
        "keyword": "공항시장역정형외과"
      },
      {
        "region": "",
        "keyword": "우장산역어깨충돌증후군"
      },
      {
        "region": "",
        "keyword": "개화역척추관협착증"
      },
      {
        "region": "",
        "keyword": "개화역정형외과"
      },
      {
        "region": "",
        "keyword": "김포경추신경근병증"
      },
      {
        "region": "",
        "keyword": "신월동척추분리증"
      },
      {
        "region": "",
        "keyword": "까치산역테니스엘보"
      },
      {
        "region": "",
        "keyword": "신월손목터널증후군"
      },
      {
        "region": "",
        "keyword": "신월정형외과"
      },
      {
        "region": "",
        "keyword": "강서정형외과골프엘보"
      },
      {
        "region": "",
        "keyword": "우장산역척추분리증"
      },
      {
        "region": "",
        "keyword": "송정역척추골절"
      },
      {
        "region": "",
        "keyword": "마곡연골연화증"
      },
      {
        "region": "",
        "keyword": "가양동무릎병원"
      },
      {
        "region": "",
        "keyword": "가양동무릎"
      },
      {
        "region": "",
        "keyword": "송정역척추"
      },
      {
        "region": "",
        "keyword": "우장산역척추"
      },
      {
        "region": "",
        "keyword": "신월손목"
      },
      {
        "region": "",
        "keyword": "김포경추"
      },
      {
        "region": "",
        "keyword": "화곡역무릎"
      },
      {
        "region": "",
        "keyword": "신월동척추"
      },
      {
        "region": "",
        "keyword": "원그로브병원무릎인대"
      },
      {
        "region": "",
        "keyword": "원그로브병원손목건초염"
      },
      {
        "region": "",
        "keyword": "행신역어깨탈구"
      },
      {
        "region": "",
        "keyword": "신방화역좌골신경통"
      },
      {
        "region": "",
        "keyword": "공항동어깨충돌증후군"
      },
      {
        "region": "",
        "keyword": "신방화좌골신경통"
      },
      {
        "region": "",
        "keyword": "오정구근막통증증후군"
      },
      {
        "region": "",
        "keyword": "송정척추골절"
      },
      {
        "region": "",
        "keyword": "강서신경외과경추신경근병증"
      },
      {
        "region": "",
        "keyword": "행신역회전근개파열"
      },
      {
        "region": "",
        "keyword": "행신회전근개파열"
      },
      {
        "region": "",
        "keyword": "발산어깨통증"
      },
      {
        "region": "",
        "keyword": "까치산역신경외과"
      },
      {
        "region": "",
        "keyword": "행신동연골연화증"
      },
      {
        "region": "",
        "keyword": "까치산신경외과"
      },
      {
        "region": "",
        "keyword": "행신연골연화증"
      },
      {
        "region": "",
        "keyword": "우장산역무지외반증"
      },
      {
        "region": "",
        "keyword": "우장산무지외반증"
      },
      {
        "region": "",
        "keyword": "까치산역발목터널증후군"
      },
      {
        "region": "",
        "keyword": "까치산발목터널증후군"
      },
      {
        "region": "",
        "keyword": "가양동무릎관절염"
      },
      {
        "region": "",
        "keyword": "발산족저근막염"
      },
      {
        "region": "",
        "keyword": "공항동슬개대퇴증후군"
      },
      {
        "region": "",
        "keyword": "공항동슬개"
      },
      {
        "region": "",
        "keyword": "오정구아킬레스건파열"
      },
      {
        "region": "",
        "keyword": "오정구아킬레스건"
      },
      {
        "region": "",
        "keyword": "송정역무릎병원"
      },
      {
        "region": "",
        "keyword": "송정역손목터널증후군"
      },
      {
        "region": "",
        "keyword": "송정역무릎연골손상"
      },
      {
        "region": "",
        "keyword": "공항시장역반월상연골판파열"
      },
      {
        "region": "",
        "keyword": "발산관절탈구"
      },
      {
        "region": "",
        "keyword": "발산역관절탈구"
      },
      {
        "region": "",
        "keyword": "우장산역수근관증후군"
      },
      {
        "region": "",
        "keyword": "우장산수근관증후군"
      },
      {
        "region": "",
        "keyword": "등촌정형외과골프엘보"
      },
      {
        "region": "",
        "keyword": "등촌정형외과"
      },
      {
        "region": "",
        "keyword": "등촌골프엘보"
      },
      {
        "region": "",
        "keyword": "행신역정형외과근막통증증후군"
      },
      {
        "region": "",
        "keyword": "행신정형외과근막통증증후군"
      },
      {
        "region": "",
        "keyword": "행신역근막통증증후군"
      },
      {
        "region": "",
        "keyword": "행신역근막통증"
      },
      {
        "region": "",
        "keyword": "발산역어깨충돌증후군"
      },
      {
        "region": "",
        "keyword": "발산어깨충돌증후군"
      },
      {
        "region": "",
        "keyword": "김포정형외과관절탈구"
      },
      {
        "region": "",
        "keyword": "김포관절탈구"
      },
      {
        "region": "",
        "keyword": "화곡역정형외과무릎관절염"
      },
      {
        "region": "",
        "keyword": "화곡정형외과무릎관절염"
      },
      {
        "region": "",
        "keyword": "화곡무릎관절염"
      },
      {
        "region": "",
        "keyword": "강서정형외과인대손상"
      },
      {
        "region": "",
        "keyword": "마곡허리디스크"
      },
      {
        "region": "",
        "keyword": "마곡역무릎관절염"
      },
      {
        "region": "",
        "keyword": "강서인대손상"
      }
    ],
    "national-pc": [
      {
        "region": "",
        "keyword": "족저근막염"
      },
      {
        "region": "",
        "keyword": "무지외반증"
      },
      {
        "region": "",
        "keyword": "목디스크증상"
      },
      {
        "region": "",
        "keyword": "팔꿈치통증"
      },
      {
        "region": "",
        "keyword": "고관절통증"
      },
      {
        "region": "",
        "keyword": "발목접질렀을때"
      },
      {
        "region": "",
        "keyword": "방아쇠수지증후군"
      },
      {
        "region": "",
        "keyword": "목이아파요"
      },
      {
        "region": "",
        "keyword": "테니스엘보"
      },
      {
        "region": "",
        "keyword": "발목통증"
      },
      {
        "region": "",
        "keyword": "지간신경종"
      },
      {
        "region": "",
        "keyword": "발목인대파열"
      },
      {
        "region": "",
        "keyword": "아킬레스건염"
      },
      {
        "region": "",
        "keyword": "발목염좌"
      },
      {
        "region": "",
        "keyword": "골프엘보"
      },
      {
        "region": "",
        "keyword": "손이저린이유"
      },
      {
        "region": "",
        "keyword": "테니스엘보치료"
      },
      {
        "region": "",
        "keyword": "아킬레스건파열"
      },
      {
        "region": "",
        "keyword": "대퇴골두무혈성괴사"
      },
      {
        "region": "",
        "keyword": "PRP주사"
      },
      {
        "region": "",
        "keyword": "팔이저려요"
      },
      {
        "region": "",
        "keyword": "엄지손가락저림"
      },
      {
        "region": "",
        "keyword": "손가락정형외과"
      },
      {
        "region": "",
        "keyword": "고관절염증"
      },
      {
        "region": "",
        "keyword": "손끝이저려요"
      },
      {
        "region": "",
        "keyword": "무지외반증증상"
      },
      {
        "region": "",
        "keyword": "발목관절염"
      },
      {
        "region": "",
        "keyword": "무릎뚝소리"
      },
      {
        "region": "",
        "keyword": "발목이아파요"
      },
      {
        "region": "",
        "keyword": "족저근막염원인"
      },
      {
        "region": "",
        "keyword": "무지외반증치료"
      },
      {
        "region": "",
        "keyword": "발바닥찌릿"
      },
      {
        "region": "",
        "keyword": "발목염좌치료"
      },
      {
        "region": "",
        "keyword": "무릎앞쪽통증"
      },
      {
        "region": "",
        "keyword": "족부정형외과"
      },
      {
        "region": "",
        "keyword": "무릎정형외과"
      },
      {
        "region": "",
        "keyword": "손목터널증후군원인"
      },
      {
        "region": "",
        "keyword": "고관절병원"
      },
      {
        "region": "",
        "keyword": "어깨통증치료병원"
      },
      {
        "region": "",
        "keyword": "고관절치료"
      },
      {
        "region": "",
        "keyword": "무지외반증원인"
      },
      {
        "region": "",
        "keyword": "수부정형외과"
      },
      {
        "region": "",
        "keyword": "발목병원"
      },
      {
        "region": "",
        "keyword": "무릎통증치료"
      },
      {
        "region": "",
        "keyword": "발목정형외과"
      },
      {
        "region": "",
        "keyword": "허리통증치료"
      },
      {
        "region": "",
        "keyword": "척추관협착증치료법"
      },
      {
        "region": "",
        "keyword": "발목염좌증상"
      },
      {
        "region": "",
        "keyword": "발정형외과"
      },
      {
        "region": "",
        "keyword": "손목건초염병원"
      },
      {
        "region": "",
        "keyword": "팔꿈치주사"
      },
      {
        "region": "",
        "keyword": "척추전방전위증치료"
      },
      {
        "region": "",
        "keyword": "고관절정형외과"
      },
      {
        "region": "",
        "keyword": "뒷목이아플때"
      },
      {
        "region": "",
        "keyword": "발목염좌병원"
      },
      {
        "region": "",
        "keyword": "족저근막염치료법"
      },
      {
        "region": "",
        "keyword": "손저림치료"
      },
      {
        "region": "",
        "keyword": "발목관절염증상"
      },
      {
        "region": "",
        "keyword": "퇴행성고관절염"
      },
      {
        "region": "",
        "keyword": "발목이아플때"
      },
      {
        "region": "",
        "keyword": "엄지발가락이아파요"
      },
      {
        "region": "",
        "keyword": "발목관절염치료"
      },
      {
        "region": "",
        "keyword": "어깨치료잘하는병원"
      },
      {
        "region": "",
        "keyword": "발목통증치료"
      },
      {
        "region": "",
        "keyword": "석회화건염치료"
      },
      {
        "region": "",
        "keyword": "발목관절염병원"
      },
      {
        "region": "",
        "keyword": "무릎치료잘하는곳"
      },
      {
        "region": "",
        "keyword": "무릎통증치료법"
      },
      {
        "region": "",
        "keyword": "목이아픈원인"
      },
      {
        "region": "",
        "keyword": "발가락통증치료"
      }
    ],
    "national-mob": [
      {
        "region": "",
        "keyword": "족저근막염"
      },
      {
        "region": "",
        "keyword": "무지외반증"
      },
      {
        "region": "",
        "keyword": "목디스크증상"
      },
      {
        "region": "",
        "keyword": "팔꿈치통증"
      },
      {
        "region": "",
        "keyword": "고관절통증"
      },
      {
        "region": "",
        "keyword": "발목접질렀을때"
      },
      {
        "region": "",
        "keyword": "방아쇠수지증후군"
      },
      {
        "region": "",
        "keyword": "목이아파요"
      },
      {
        "region": "",
        "keyword": "테니스엘보"
      },
      {
        "region": "",
        "keyword": "발목통증"
      },
      {
        "region": "",
        "keyword": "지간신경종"
      },
      {
        "region": "",
        "keyword": "발목인대파열"
      },
      {
        "region": "",
        "keyword": "아킬레스건염"
      },
      {
        "region": "",
        "keyword": "발목염좌"
      },
      {
        "region": "",
        "keyword": "골프엘보"
      },
      {
        "region": "",
        "keyword": "손이저린이유"
      },
      {
        "region": "",
        "keyword": "테니스엘보치료"
      },
      {
        "region": "",
        "keyword": "아킬레스건파열"
      },
      {
        "region": "",
        "keyword": "대퇴골두무혈성괴사"
      },
      {
        "region": "",
        "keyword": "PRP주사"
      },
      {
        "region": "",
        "keyword": "팔이저려요"
      },
      {
        "region": "",
        "keyword": "엄지손가락저림"
      },
      {
        "region": "",
        "keyword": "손가락정형외과"
      },
      {
        "region": "",
        "keyword": "고관절염증"
      },
      {
        "region": "",
        "keyword": "손끝이저려요"
      },
      {
        "region": "",
        "keyword": "무지외반증증상"
      },
      {
        "region": "",
        "keyword": "발목관절염"
      },
      {
        "region": "",
        "keyword": "무릎뚝소리"
      },
      {
        "region": "",
        "keyword": "발목이아파요"
      },
      {
        "region": "",
        "keyword": "족저근막염원인"
      },
      {
        "region": "",
        "keyword": "무지외반증치료"
      },
      {
        "region": "",
        "keyword": "발바닥찌릿"
      },
      {
        "region": "",
        "keyword": "발목염좌치료"
      },
      {
        "region": "",
        "keyword": "무릎앞쪽통증"
      },
      {
        "region": "",
        "keyword": "족부정형외과"
      },
      {
        "region": "",
        "keyword": "무릎정형외과"
      },
      {
        "region": "",
        "keyword": "손목터널증후군원인"
      },
      {
        "region": "",
        "keyword": "고관절병원"
      },
      {
        "region": "",
        "keyword": "어깨통증치료병원"
      },
      {
        "region": "",
        "keyword": "고관절치료"
      },
      {
        "region": "",
        "keyword": "무지외반증원인"
      },
      {
        "region": "",
        "keyword": "수부정형외과"
      },
      {
        "region": "",
        "keyword": "발목병원"
      },
      {
        "region": "",
        "keyword": "무릎통증치료"
      },
      {
        "region": "",
        "keyword": "발목정형외과"
      },
      {
        "region": "",
        "keyword": "허리통증치료"
      },
      {
        "region": "",
        "keyword": "척추관협착증치료법"
      },
      {
        "region": "",
        "keyword": "발목염좌증상"
      },
      {
        "region": "",
        "keyword": "발정형외과"
      },
      {
        "region": "",
        "keyword": "손목건초염병원"
      },
      {
        "region": "",
        "keyword": "팔꿈치주사"
      },
      {
        "region": "",
        "keyword": "척추전방전위증치료"
      },
      {
        "region": "",
        "keyword": "고관절정형외과"
      },
      {
        "region": "",
        "keyword": "뒷목이아플때"
      },
      {
        "region": "",
        "keyword": "발목염좌병원"
      },
      {
        "region": "",
        "keyword": "족저근막염치료법"
      },
      {
        "region": "",
        "keyword": "손저림치료"
      },
      {
        "region": "",
        "keyword": "발목관절염증상"
      },
      {
        "region": "",
        "keyword": "퇴행성고관절염"
      },
      {
        "region": "",
        "keyword": "발목이아플때"
      },
      {
        "region": "",
        "keyword": "엄지발가락이아파요"
      },
      {
        "region": "",
        "keyword": "발목관절염치료"
      },
      {
        "region": "",
        "keyword": "어깨치료잘하는병원"
      },
      {
        "region": "",
        "keyword": "발목통증치료"
      },
      {
        "region": "",
        "keyword": "석회화건염치료"
      },
      {
        "region": "",
        "keyword": "발목관절염병원"
      },
      {
        "region": "",
        "keyword": "무릎치료잘하는곳"
      },
      {
        "region": "",
        "keyword": "무릎통증치료법"
      },
      {
        "region": "",
        "keyword": "목이아픈원인"
      },
      {
        "region": "",
        "keyword": "발가락통증치료"
      }
    ],
    "other-pc": [],
    "other-mob": []
  },
  "sheetTitles": {
    "regional-pc": "2026 지역 PC",
    "regional-mob": "2026 지역 MOB",
    "national-pc": "2026 전국 PC",
    "national-mob": "2026 전국 MOB",
    "other-pc": "2026 기타 PC",
    "other-mob": "2026 기타 MOB"
  },
  "scoringNote": "API 자동 탭(지도/카페/블로그/보도자료/웹)은 1위=3점, 2~5위=2점, 6~10위=1점, 미노출=0점.",
  "blogRequirePostMonth": true,
  "keywordChannels": {
    "마곡정형외과": "all",
    "화곡역정형외과": "all",
    "김포정형외과": "all",
    "마곡역정형외과": "all",
    "발산역정형외과": "all",
    "화곡동정형외과": "all",
    "강서구정형외과": "all",
    "강서정형외과": "all",
    "마곡동정형외과": "all",
    "발산정형외과": "all",
    "김포신경외과": "all",
    "우장산역정형외과": "all",
    "가양동정형외과": "all",
    "신방화역정형외과": "all",
    "강서구신경외과": "all",
    "강서신경외과": "all",
    "송정역정형외과": "all",
    "마곡신경외과": "all",
    "화곡역신경외과": "all",
    "마곡역신경외과": "all",
    "원그로브병원": "all",
    "원그로브정형외과": "all",
    "발산역신경외과": "all",
    "화곡동신경외과": "all",
    "발산역허리디스크": "all",
    "발산신경외과": "all",
    "마곡동신경외과": "all",
    "우장산역신경외과": "all",
    "가양동신경외과": "all",
    "발산역오십견": "all",
    "발산역어깨통증": "all",
    "마곡역퇴행성관절염": "all",
    "마곡역오십견": "all",
    "발산역퇴행성관절염": "all",
    "마곡역무릎병원": "all",
    "발산역디스크치료": "all",
    "발산역족저근막염": "all",
    "발산역족부정형외과": "all",
    "발산역아킬레스건염": "all",
    "발산역석회화건염": "all",
    "발산역발목치료": "all",
    "발산역발목정형외과": "all",
    "발산역발목병원": "all",
    "발산역발목관절염": "all",
    "발산역무지외반증": "all",
    "발산역무릎정형외과": "all",
    "발산역무릎관절염": "all",
    "마곡퇴행성관절염": "all",
    "마곡족저근막염": "all",
    "마곡족부정형외과": "all",
    "마곡오십견": "all",
    "마곡역족저근막염": "all",
    "마곡역족부정형외과": "all",
    "마곡역아킬레스건염": "all",
    "마곡역석회화건염": "all",
    "마곡역발목정형외과": "all",
    "마곡역발목병원": "all",
    "마곡역발목관절염": "all",
    "마곡역무릎정형외과": "all",
    "화곡역무릎관절염": "all",
    "공항시장역테니스엘보": "all",
    "공항시장역정형외과": "all",
    "우장산역어깨충돌증후군": "all",
    "개화역척추관협착증": "all",
    "개화역정형외과": "all",
    "김포경추신경근병증": "all",
    "신월동척추분리증": "all",
    "까치산역테니스엘보": "all",
    "신월손목터널증후군": "all",
    "신월정형외과": "all",
    "강서정형외과골프엘보": "all",
    "우장산역척추분리증": "all",
    "송정역척추골절": "all",
    "마곡연골연화증": "all",
    "가양동무릎병원": "all",
    "가양동무릎": "all",
    "송정역척추": "all",
    "우장산역척추": "all",
    "신월손목": "all",
    "김포경추": "all",
    "화곡역무릎": "all",
    "신월동척추": "all",
    "원그로브병원무릎인대": "all",
    "원그로브병원손목건초염": "all",
    "행신역어깨탈구": "all",
    "신방화역좌골신경통": "all",
    "공항동어깨충돌증후군": "all",
    "신방화좌골신경통": "all",
    "오정구근막통증증후군": "all",
    "송정척추골절": "all",
    "강서신경외과경추신경근병증": "all",
    "행신역회전근개파열": "all",
    "행신회전근개파열": "all",
    "발산어깨통증": "all",
    "까치산역신경외과": "all",
    "행신동연골연화증": "all",
    "까치산신경외과": "all",
    "행신연골연화증": "all",
    "우장산역무지외반증": "all",
    "우장산무지외반증": "all",
    "까치산역발목터널증후군": "all",
    "까치산발목터널증후군": "all",
    "가양동무릎관절염": "all",
    "발산족저근막염": "all",
    "공항동슬개대퇴증후군": "all",
    "공항동슬개": "all",
    "오정구아킬레스건파열": "all",
    "오정구아킬레스건": "all",
    "송정역무릎병원": "all",
    "송정역손목터널증후군": "all",
    "송정역무릎연골손상": "all",
    "공항시장역반월상연골판파열": "all",
    "발산관절탈구": "all",
    "발산역관절탈구": "all",
    "우장산역수근관증후군": "all",
    "우장산수근관증후군": "all",
    "등촌정형외과골프엘보": "all",
    "등촌정형외과": "all",
    "등촌골프엘보": "all",
    "행신역정형외과근막통증증후군": "all",
    "행신정형외과근막통증증후군": "all",
    "행신역근막통증증후군": "all",
    "행신역근막통증": "all",
    "발산역어깨충돌증후군": "all",
    "발산어깨충돌증후군": "all",
    "김포정형외과관절탈구": "all",
    "김포관절탈구": "all",
    "화곡역정형외과무릎관절염": "all",
    "화곡정형외과무릎관절염": "all",
    "화곡무릎관절염": "all",
    "강서정형외과인대손상": "all",
    "마곡허리디스크": "all",
    "마곡역무릎관절염": "all",
    "강서인대손상": "all",
    "족저근막염": "all",
    "무지외반증": "all",
    "목디스크증상": "all",
    "팔꿈치통증": "all",
    "고관절통증": "all",
    "발목접질렀을때": "all",
    "방아쇠수지증후군": "all",
    "목이아파요": "all",
    "테니스엘보": "all",
    "발목통증": "all",
    "지간신경종": "all",
    "발목인대파열": "all",
    "아킬레스건염": "all",
    "발목염좌": "all",
    "골프엘보": "all",
    "손이저린이유": "all",
    "테니스엘보치료": "all",
    "아킬레스건파열": "all",
    "대퇴골두무혈성괴사": "all",
    "PRP주사": "all",
    "팔이저려요": "all",
    "엄지손가락저림": "all",
    "손가락정형외과": "all",
    "고관절염증": "all",
    "손끝이저려요": "all",
    "무지외반증증상": "all",
    "발목관절염": "all",
    "무릎뚝소리": "all",
    "발목이아파요": "all",
    "족저근막염원인": "all",
    "무지외반증치료": "all",
    "발바닥찌릿": "all",
    "발목염좌치료": "all",
    "무릎앞쪽통증": "all",
    "족부정형외과": "all",
    "무릎정형외과": "all",
    "손목터널증후군원인": "all",
    "고관절병원": "all",
    "어깨통증치료병원": "all",
    "고관절치료": "all",
    "무지외반증원인": "all",
    "수부정형외과": "all",
    "발목병원": "all",
    "무릎통증치료": "all",
    "발목정형외과": "all",
    "허리통증치료": "all",
    "척추관협착증치료법": "all",
    "발목염좌증상": "all",
    "발정형외과": "all",
    "손목건초염병원": "all",
    "팔꿈치주사": "all",
    "척추전방전위증치료": "all",
    "고관절정형외과": "all",
    "뒷목이아플때": "all",
    "발목염좌병원": "all",
    "족저근막염치료법": "all",
    "손저림치료": "all",
    "발목관절염증상": "all",
    "퇴행성고관절염": "all",
    "발목이아플때": "all",
    "엄지발가락이아파요": "all",
    "발목관절염치료": "all",
    "어깨치료잘하는병원": "all",
    "발목통증치료": "all",
    "석회화건염치료": "all",
    "발목관절염병원": "all",
    "무릎치료잘하는곳": "all",
    "무릎통증치료법": "all",
    "목이아픈원인": "all",
    "발가락통증치료": "all"
  },
  "keywordScopes": {
    "마곡정형외과": "regional",
    "화곡역정형외과": "regional",
    "김포정형외과": "regional",
    "마곡역정형외과": "regional",
    "발산역정형외과": "regional",
    "화곡동정형외과": "regional",
    "강서구정형외과": "regional",
    "강서정형외과": "regional",
    "마곡동정형외과": "regional",
    "발산정형외과": "regional",
    "김포신경외과": "regional",
    "우장산역정형외과": "regional",
    "가양동정형외과": "regional",
    "신방화역정형외과": "regional",
    "강서구신경외과": "regional",
    "강서신경외과": "regional",
    "송정역정형외과": "regional",
    "마곡신경외과": "regional",
    "화곡역신경외과": "regional",
    "마곡역신경외과": "regional",
    "원그로브병원": "regional",
    "원그로브정형외과": "regional",
    "발산역신경외과": "regional",
    "화곡동신경외과": "regional",
    "발산역허리디스크": "regional",
    "발산신경외과": "regional",
    "마곡동신경외과": "regional",
    "우장산역신경외과": "regional",
    "가양동신경외과": "regional",
    "발산역오십견": "regional",
    "발산역어깨통증": "regional",
    "마곡역퇴행성관절염": "regional",
    "마곡역오십견": "regional",
    "발산역퇴행성관절염": "regional",
    "마곡역무릎병원": "regional",
    "발산역디스크치료": "regional",
    "발산역족저근막염": "regional",
    "발산역족부정형외과": "regional",
    "발산역아킬레스건염": "regional",
    "발산역석회화건염": "regional",
    "발산역발목치료": "regional",
    "발산역발목정형외과": "regional",
    "발산역발목병원": "regional",
    "발산역발목관절염": "regional",
    "발산역무지외반증": "regional",
    "발산역무릎정형외과": "regional",
    "발산역무릎관절염": "regional",
    "마곡퇴행성관절염": "regional",
    "마곡족저근막염": "regional",
    "마곡족부정형외과": "regional",
    "마곡오십견": "regional",
    "마곡역족저근막염": "regional",
    "마곡역족부정형외과": "regional",
    "마곡역아킬레스건염": "regional",
    "마곡역석회화건염": "regional",
    "마곡역발목정형외과": "regional",
    "마곡역발목병원": "regional",
    "마곡역발목관절염": "regional",
    "마곡역무릎정형외과": "regional",
    "화곡역무릎관절염": "regional",
    "공항시장역테니스엘보": "regional",
    "공항시장역정형외과": "regional",
    "우장산역어깨충돌증후군": "regional",
    "개화역척추관협착증": "regional",
    "개화역정형외과": "regional",
    "김포경추신경근병증": "regional",
    "신월동척추분리증": "regional",
    "까치산역테니스엘보": "regional",
    "신월손목터널증후군": "regional",
    "신월정형외과": "regional",
    "강서정형외과골프엘보": "regional",
    "우장산역척추분리증": "regional",
    "송정역척추골절": "regional",
    "마곡연골연화증": "regional",
    "가양동무릎병원": "regional",
    "가양동무릎": "regional",
    "송정역척추": "regional",
    "우장산역척추": "regional",
    "신월손목": "regional",
    "김포경추": "regional",
    "화곡역무릎": "regional",
    "신월동척추": "regional",
    "원그로브병원무릎인대": "regional",
    "원그로브병원손목건초염": "regional",
    "행신역어깨탈구": "regional",
    "신방화역좌골신경통": "regional",
    "공항동어깨충돌증후군": "regional",
    "신방화좌골신경통": "regional",
    "오정구근막통증증후군": "regional",
    "송정척추골절": "regional",
    "강서신경외과경추신경근병증": "regional",
    "행신역회전근개파열": "regional",
    "행신회전근개파열": "regional",
    "발산어깨통증": "regional",
    "까치산역신경외과": "regional",
    "행신동연골연화증": "regional",
    "까치산신경외과": "regional",
    "행신연골연화증": "regional",
    "우장산역무지외반증": "regional",
    "우장산무지외반증": "regional",
    "까치산역발목터널증후군": "regional",
    "까치산발목터널증후군": "regional",
    "가양동무릎관절염": "regional",
    "발산족저근막염": "regional",
    "공항동슬개대퇴증후군": "regional",
    "공항동슬개": "regional",
    "오정구아킬레스건파열": "regional",
    "오정구아킬레스건": "regional",
    "송정역무릎병원": "regional",
    "송정역손목터널증후군": "regional",
    "송정역무릎연골손상": "regional",
    "공항시장역반월상연골판파열": "regional",
    "발산관절탈구": "regional",
    "발산역관절탈구": "regional",
    "우장산역수근관증후군": "regional",
    "우장산수근관증후군": "regional",
    "등촌정형외과골프엘보": "regional",
    "등촌정형외과": "regional",
    "등촌골프엘보": "regional",
    "행신역정형외과근막통증증후군": "regional",
    "행신정형외과근막통증증후군": "regional",
    "행신역근막통증증후군": "regional",
    "행신역근막통증": "regional",
    "발산역어깨충돌증후군": "regional",
    "발산어깨충돌증후군": "regional",
    "김포정형외과관절탈구": "regional",
    "김포관절탈구": "regional",
    "화곡역정형외과무릎관절염": "regional",
    "화곡정형외과무릎관절염": "regional",
    "화곡무릎관절염": "regional",
    "강서정형외과인대손상": "regional",
    "마곡허리디스크": "regional",
    "마곡역무릎관절염": "regional",
    "강서인대손상": "regional",
    "족저근막염": "national",
    "무지외반증": "national",
    "목디스크증상": "national",
    "팔꿈치통증": "national",
    "고관절통증": "national",
    "발목접질렀을때": "national",
    "방아쇠수지증후군": "national",
    "목이아파요": "national",
    "테니스엘보": "national",
    "발목통증": "national",
    "지간신경종": "national",
    "발목인대파열": "national",
    "아킬레스건염": "national",
    "발목염좌": "national",
    "골프엘보": "national",
    "손이저린이유": "national",
    "테니스엘보치료": "national",
    "아킬레스건파열": "national",
    "대퇴골두무혈성괴사": "national",
    "PRP주사": "national",
    "팔이저려요": "national",
    "엄지손가락저림": "national",
    "손가락정형외과": "national",
    "고관절염증": "national",
    "손끝이저려요": "national",
    "무지외반증증상": "national",
    "발목관절염": "national",
    "무릎뚝소리": "national",
    "발목이아파요": "national",
    "족저근막염원인": "national",
    "무지외반증치료": "national",
    "발바닥찌릿": "national",
    "발목염좌치료": "national",
    "무릎앞쪽통증": "national",
    "족부정형외과": "national",
    "무릎정형외과": "national",
    "손목터널증후군원인": "national",
    "고관절병원": "national",
    "어깨통증치료병원": "national",
    "고관절치료": "national",
    "무지외반증원인": "national",
    "수부정형외과": "national",
    "발목병원": "national",
    "무릎통증치료": "national",
    "발목정형외과": "national",
    "허리통증치료": "national",
    "척추관협착증치료법": "national",
    "발목염좌증상": "national",
    "발정형외과": "national",
    "손목건초염병원": "national",
    "팔꿈치주사": "national",
    "척추전방전위증치료": "national",
    "고관절정형외과": "national",
    "뒷목이아플때": "national",
    "발목염좌병원": "national",
    "족저근막염치료법": "national",
    "손저림치료": "national",
    "발목관절염증상": "national",
    "퇴행성고관절염": "national",
    "발목이아플때": "national",
    "엄지발가락이아파요": "national",
    "발목관절염치료": "national",
    "어깨치료잘하는병원": "national",
    "발목통증치료": "national",
    "석회화건염치료": "national",
    "발목관절염병원": "national",
    "무릎치료잘하는곳": "national",
    "무릎통증치료법": "national",
    "목이아픈원인": "national",
    "발가락통증치료": "national"
  }
}